Metadata-Version: 2.1
Name: almgroad0770i
Version: 1.0
Summary: Is a FREE asynchronous library from reverse engineered Shazam API written in Python 3.6+ with asyncio and aiohttp. Includes all the methods that Shazam has, including searching for a song by file.
Home-page: https://github.com/dotX12/ShazamIO
Author: BKXBB
License: UNKNOWN
Platform: UNKNOWN
Classifier: Programming Language :: Python :: 3
Classifier: License :: OSI Approved :: MIT License
Classifier: Operating System :: OS Independent
License-File: LICENSE.txt
